uz_sdk/__init__.py
uz_sdk/sdk.py
uz_sdk/utils.py
UZ_SDK-0.0.3.dist-info/METADATA
UZ_SDK-0.0.3.dist-info/WHEEL
UZ_SDK-0.0.3.dist-info/top_level.txt
UZ_SDK-0.0.3.dist-info/RECORD
